relay/__init__.py
relay/auth/account.py
relay/auth/credentials.py
relay/auth/storage.py
relay/cli/_utils.py
relay/cli/commands/accounts.py
relay/cli/commands/messages.py
relay/cli/main.py
relay/exceptions.py
relay/models/account.py
relay/models/base.py
relay/models/message.py
relay/providers/imap.py
relay/providers/smtp.py
relay/providers/utils.py
relaycli-0.0.1a3.dist-info/WHEEL
relaycli-0.0.1a3.dist-info/entry_points.txt
relaycli-0.0.1a3.dist-info/METADATA
relaycli-0.0.1a3.dist-info/RECORD
