Metadata-Version: 2.3
Name: relaycli
Version: 0.0.1a3
Summary: Open-source IMAP-native replacement for Gmail API
Keywords: cli,imap,smtp,gmail,outlook,email,inbox
Author: Relay team
Author-email: Relay team <support@relaycli.com>
License:                                  Apache License
Classifier: Development Status :: 3 - Alpha
Classifier: Environment :: Console
Classifier: Framework :: Pydantic
Classifier: Intended Audience :: Developers
Classifier: License :: OSI Approved :: Apache Software License
Classifier: Natural Language :: English
Classifier: Operating System :: OS Independent
Classifier: Programming Language :: Python
Classifier: Programming Language :: Python :: 3
Classifier: Programming Language :: Python :: 3 :: Only
Classifier: Programming Language :: Python :: 3.11
Classifier: Programming Language :: Python :: 3.12
Classifier: Programming Language :: Python :: 3.13
Classifier: Programming Language :: Python :: Implementation :: CPython
Classifier: Topic :: Communications :: Email
Classifier: Topic :: Communications :: Email :: Post-Office
Classifier: Topic :: Communications :: Email :: Post-Office :: IMAP
Classifier: Topic :: Communications :: Email :: Post-Office :: POP3
Classifier: Topic :: Software Development
Classifier: Topic :: Software Development :: Libraries
Classifier: Topic :: Software Development :: Libraries :: Python Modules
Classifier: Topic :: Software Development :: User Interfaces
Classifier: Topic :: Software Development :: Version Control :: Git
Classifier: Typing :: Typed
Requires-Dist: typer>=0.16.0,<1.0.0
Requires-Dist: rich>=13.0.0,<14.0.0
Requires-Dist: questionary>=2.0.0,<3.0.0
Requires-Dist: pydantic>=2.10.0,<3.0.0
Requires-Dist: email-validator>=2.0.0,<3.0.0
Requires-Dist: cryptography>=44.0.0,<46.0.0
Requires-Dist: beautifulsoup4>=4.12.3,<5.0.0
Requires-Dist: html2text>=2025.4.15
Requires-Dist: ruff==0.12.3 ; extra == 'quality'
Requires-Dist: ty==0.0.1a14 ; extra == 'quality'
Requires-Dist: pre-commit==4.2.0 ; extra == 'quality'
Requires-Dist: pytest==8.4.1 ; extra == 'test'
Requires-Dist: pytest-cov==6.2.1 ; extra == 'test'
Requires-Dist: pytest-pretty==1.3.0 ; extra == 'test'
Requires-Dist: pytest-mock==3.14.1 ; extra == 'test'
Requires-Python: >=3.11, <4.0
Project-URL: documentation, https://docs.relaycli.com
Project-URL: homepage, https://relaycli.com
Project-URL: issues, https://github.com/relaycli/relay/issues
Project-URL: logo, https://zugjkckdxhiamdlkxfmv.supabase.co/storage/v1/object/public/assets//logo_dark.svg
Project-URL: releasenotes, https://github.com/relaycli/relay/releases
Project-URL: repository, https://github.com/relaycli/relay
Provides-Extra: quality
Provides-Extra: test
